scipy_steadystate/__init__.py
scipy_steadystate/steady_state.py
scipy_steadystate/itertools/__init__.py
scipy_steadystate/numerics/__init__.py
scipy_steadystate/numerics/numerical_integration_iterator.py
scipy_steadystate/numerics/prod.py
scipy_steadystate/numerics/recursion_iterator.py
scipy_steadystate/numerics/algorithms/__init__.py
scipy_steadystate/numerics/algorithms/backward_euler.py
scipy_steadystate/numerics/algorithms/envelope_following_method.py
scipy_steadystate/numerics/algorithms/forward_euler.py
scipy_steadystate/numerics/algorithms/midpoint_method.py
scipy_steadystate/numerics/algorithms/runge_kutta_method.py
scipy_steadystate/numerics/algorithms/trapezoidal_rule.py
scipy_steadystate-0.1.dist-info/LICENSE
scipy_steadystate-0.1.dist-info/METADATA
scipy_steadystate-0.1.dist-info/WHEEL
scipy_steadystate-0.1.dist-info/top_level.txt
scipy_steadystate-0.1.dist-info/RECORD
